pipedantic/__init__.py
pipedantic/utils.py
pipedantic-0.2.0.dist-info/LICENSE
pipedantic-0.2.0.dist-info/METADATA
pipedantic-0.2.0.dist-info/WHEEL
pipedantic-0.2.0.dist-info/RECORD
